fr_models/__init__.py
fr_models/analytic_models.py
fr_models/constraints.py
fr_models/criteria.py
fr_models/exceptions.py
fr_models/gridtools.py
fr_models/interp.py
fr_models/kernels.py
fr_models/numerical_models.py
fr_models/optimize.py
fr_models/periodic.py
fr_models/regularizers.py
fr_models/response_models.py
fr_models/timeout.py
fr_models/viz.py
fr_models/_torch/__init__.py
fr_models/_torch/core.py
fr_models/_torch/integrate.py
fr_models/_torch/linalg.py
fr_models/_torch/nn.py
fr_models/_torch/parametrize.py
fr_models/_torch/stats.py
fr_models/_torch/utils.py
fr_models/geom/__init__.py
fr_models/geom/curve.py
fr_models/geom/manifold.py
fr_models/geom/plane.py
fr_models-0.1.14.dist-info/LICENSE
fr_models-0.1.14.dist-info/METADATA
fr_models-0.1.14.dist-info/WHEEL
fr_models-0.1.14.dist-info/top_level.txt
fr_models-0.1.14.dist-info/RECORD
