Metadata-Version: 2.1
Name: fr-models
Version: 0.1.14
Summary: A python package for simulating and fitting firing rate models using PyTorch backend.
Author: Ho Yin Chau
License: MIT License
Project-URL: repository, https://github.com/hchau630/fr-models
Classifier: License :: OSI Approved :: MIT License
Classifier: Natural Language :: English
Classifier: Operating System :: OS Independent
Classifier: Programming Language :: Python :: 3.9
Requires-Python: >=3.9
License-File: LICENSE
Requires-Dist: numpy
Requires-Dist: matplotlib
Requires-Dist: scipy
Requires-Dist: torch
Requires-Dist: torchdiffeq
Requires-Dist: hyclib >=0.1.15
